zeitgeber/__init__.py
zeitgeber/rle.py
zeitgeber/zeitgeber.py
zeitgeber-0.0.2.dist-info/METADATA
zeitgeber-0.0.2.dist-info/WHEEL
zeitgeber-0.0.2.dist-info/top_level.txt
zeitgeber-0.0.2.dist-info/RECORD
