Metadata-Version: 2.1
Name: zeitgeber
Version: 0.0.2
Summary: A library with utils to work with circadian time timeseries and plot them
